{
	"name": "MoviesDB2022",
	"properties": {
		"linkedServiceName": {
			"referenceName": "datalakestoragenk",
			"type": "LinkedServiceReference"
		},
		"annotations": [],
		"type": "DelimitedText",
		"typeProperties": {
			"location": {
				"type": "AzureBlobFSLocation",
				"fileName": "MoviesDB2022.csv",
				"folderPath": "data",
				"fileSystem": "testcontainer"
			},
			"columnDelimiter": ",",
			"escapeChar": "\\",
			"firstRowAsHeader": true,
			"quoteChar": "\""
		},
		"schema": [
			{
				"name": "movie",
				"type": "String"
			},
			{
				"name": "title",
				"type": "String"
			},
			{
				"name": "genres",
				"type": "String"
			},
			{
				"name": "year",
				"type": "String"
			},
			{
				"name": "Rating",
				"type": "String"
			},
			{
				"name": "RottenTomato",
				"type": "String"
			}
		]
	}
}